static_embed-0.1.1.dist-info/METADATA
static_embed-0.1.1.dist-info/WHEEL
static_embed.libs/libcom_err-2abe824b.so.2
static_embed.libs/libcrypto-d3570994.so.10
static_embed.libs/libgssapi_krb5-497db0c6.so.2
static_embed.libs/libk5crypto-b1f99d5c.so.3
static_embed.libs/libkeyutils-dfe70bd6.so.1
static_embed.libs/libkrb5-fcafa220.so.3
static_embed.libs/libkrb5support-d0bcff84.so.0
static_embed.libs/libpcre-9513aab5.so.1
static_embed.libs/libselinux-0922c95c.so.1
static_embed.libs/libssl-cd1d6220.so.10
static_embed/__init__.py
static_embed/static_embed.abi3.so
static_embed-0.1.1.dist-info/RECORD
