Metadata-Version: 2.4
Name: static_embed
Version: 0.1.1
Summary: Static sentence embedding via Rust + Candle wrapped for Python
Author-email: Alon Agmon <alon.agmon@gmail.com>
License: MIT
Requires-Python: >=3.8
